{
  "appInfo" : {
    "build" : "222.4345.14",
    "buildDate" : "2022-10-05T05:01:02.89Z[UTC]",
    "productCode" : "WS",
    "generated" : "2023-02-22T21:59:06.896576Z",
    "os" : "macOS 12.3.1",
    "runtime" : "JetBrains s.r.o. 17.0.4.1 17.0.4.1+7-b469.62"
  },
  "runtimeInfo" : {
    "maxMemory" : 536870912,
    "numberOfProcessors" : 8,
    "maxNumberOfIndexingThreads" : 4,
    "maxSizeOfFileForIntelliSense" : 2560000,
    "maxSizeOfFileForContentLoading" : 20971520
  },
  "projectIndexingHistory" : {
    "projectName" : "locationTest",
    "times" : {
      "indexingReason" : "On project open",
      "scanningType" : "FULL_ON_PROJECT_OPEN",
      "totalUpdatingTime" : 468558666,
      "indexingTime" : 0,
      "contentLoadingVisibleTime" : 0,
      "creatingIteratorsTime" : 6390000,
      "scanFilesTime" : 388402000,
      "pushPropertiesTime" : 1299000,
      "indexExtensionsTime" : 0,
      "isAppliedAllValuesSeparately" : true,
      "separateApplyingIndexesVisibleTime" : 0,
      "updatingStart" : "2023-02-22T21:59:06.425585Z",
      "updatingEnd" : "2023-02-22T21:59:06.894151Z",
      "totalSuspendedTime" : 0,
      "wasInterrupted" : false
    },
    "fileCount" : {
      "numberOfFileProviders" : 16,
      "numberOfScannedFiles" : 437,
      "numberOfFilesIndexedByInfrastructureExtensionsDuringScan" : 0,
      "numberOfFilesScheduledForIndexingAfterScan" : 0,
      "numberOfFilesIndexedByInfrastructureExtensionsDuringIndexingStage" : 0,
      "numberOfFilesIndexedWithLoadingContent" : 0
    },
    "totalStatsPerFileType" : [ ],
    "totalStatsPerIndexer" : [ ],
    "scanningStatistics" : [ {
      "providerName" : "Indexable set contributor 'com.intellij.javaee.ExternalResourcesRootsProvider@29ec2b36' (non-project)",
      "numberOfScannedFiles" : 218,
      "numberOfSkippedFiles" : 4,
      "numberOfFilesForIndexing" : 0,
      "numberOfFilesFullyIndexedByInfrastructureExtensions" : 0,
      "filesFullyIndexedByInfrastructureExtensions" : [ ],
      "statusTime" : 276464417,
      "scanningTime" : 283302671,
      "timeProcessingUpToDateFiles" : 25544074,
      "timeUpdatingContentLessIndexes" : 211126,
      "timeIndexingWithoutContent" : 0,
      "roots" : [ ]
    }, {
      "providerName" : "Module 'locationTest' (locationTest)",
      "numberOfScannedFiles" : 7,
      "numberOfSkippedFiles" : 0,
      "numberOfFilesForIndexing" : 0,
      "numberOfFilesFullyIndexedByInfrastructureExtensions" : 0,
      "filesFullyIndexedByInfrastructureExtensions" : [ ],
      "statusTime" : 261067708,
      "scanningTime" : 272886042,
      "timeProcessingUpToDateFiles" : 52957,
      "timeUpdatingContentLessIndexes" : 29541,
      "timeIndexingWithoutContent" : 0,
      "roots" : [ ]
    }, {
      "providerName" : "Indexable set contributor 'JS required libraries' (project)",
      "numberOfScannedFiles" : 44,
      "numberOfSkippedFiles" : 34,
      "numberOfFilesForIndexing" : 0,
      "numberOfFilesFullyIndexedByInfrastructureExtensions" : 0,
      "filesFullyIndexedByInfrastructureExtensions" : [ ],
      "statusTime" : 75034583,
      "scanningTime" : 75231837,
      "timeProcessingUpToDateFiles" : 42803834,
      "timeUpdatingContentLessIndexes" : 111162,
      "timeIndexingWithoutContent" : 0,
      "roots" : [ ]
    }, {
      "providerName" : "Synthetic library 'Node.js Core'",
      "numberOfScannedFiles" : 88,
      "numberOfSkippedFiles" : 0,
      "numberOfFilesForIndexing" : 0,
      "numberOfFilesFullyIndexedByInfrastructureExtensions" : 0,
      "filesFullyIndexedByInfrastructureExtensions" : [ ],
      "statusTime" : 54932540,
      "scanningTime" : 55632917,
      "timeProcessingUpToDateFiles" : 16418938,
      "timeUpdatingContentLessIndexes" : 286959,
      "timeIndexingWithoutContent" : 0,
      "roots" : [ ]
    }, {
      "providerName" : "Indexable set contributor 'Scratches & Consoles' (non-project)",
      "numberOfScannedFiles" : 24,
      "numberOfSkippedFiles" : 0,
      "numberOfFilesForIndexing" : 0,
      "numberOfFilesFullyIndexedByInfrastructureExtensions" : 0,
      "filesFullyIndexedByInfrastructureExtensions" : [ ],
      "statusTime" : 40299500,
      "scanningTime" : 51082120,
      "timeProcessingUpToDateFiles" : 14815993,
      "timeUpdatingContentLessIndexes" : 58626,
      "timeIndexingWithoutContent" : 0,
      "roots" : [ ]
    }, {
      "providerName" : "Indexable set contributor 'TypeScript bundled libraries' (project)",
      "numberOfScannedFiles" : 33,
      "numberOfSkippedFiles" : 38,
      "numberOfFilesForIndexing" : 0,
      "numberOfFilesFullyIndexedByInfrastructureExtensions" : 0,
      "filesFullyIndexedByInfrastructureExtensions" : [ ],
      "statusTime" : 44159460,
      "scanningTime" : 44261959,
      "timeProcessingUpToDateFiles" : 30737555,
      "timeUpdatingContentLessIndexes" : 64838,
      "timeIndexingWithoutContent" : 0,
      "roots" : [ ]
    }, {
      "providerName" : "Indexable set contributor 'org.jetbrains.plugins.scss.index.SassScssIndexedRootProvider@112603f9' (non-project)",
      "numberOfScannedFiles" : 8,
      "numberOfSkippedFiles" : 0,
      "numberOfFilesForIndexing" : 0,
      "numberOfFilesFullyIndexedByInfrastructureExtensions" : 0,
      "filesFullyIndexedByInfrastructureExtensions" : [ ],
      "statusTime" : 38182250,
      "scanningTime" : 38215001,
      "timeProcessingUpToDateFiles" : 9673749,
      "timeUpdatingContentLessIndexes" : 23415,
      "timeIndexingWithoutContent" : 0,
      "roots" : [ ]
    }, {
      "providerName" : "Indexable set contributor 'com.intellij.httpClient.http.request.HttpRequestCollectionProvider@7d7b0915' (non-project)",
      "numberOfScannedFiles" : 2,
      "numberOfSkippedFiles" : 0,
      "numberOfFilesForIndexing" : 0,
      "numberOfFilesFullyIndexedByInfrastructureExtensions" : 0,
      "filesFullyIndexedByInfrastructureExtensions" : [ ],
      "statusTime" : 26764459,
      "scanningTime" : 32306375,
      "timeProcessingUpToDateFiles" : 5169584,
      "timeUpdatingContentLessIndexes" : 3667,
      "timeIndexingWithoutContent" : 0,
      "roots" : [ ]
    }, {
      "providerName" : "Indexable set contributor 'JS required libraries' (non-project)",
      "numberOfScannedFiles" : 12,
      "numberOfSkippedFiles" : 0,
      "numberOfFilesForIndexing" : 0,
      "numberOfFilesFullyIndexedByInfrastructureExtensions" : 0,
      "filesFullyIndexedByInfrastructureExtensions" : [ ],
      "statusTime" : 31911291,
      "scanningTime" : 31953625,
      "timeProcessingUpToDateFiles" : 25644664,
      "timeUpdatingContentLessIndexes" : 26292,
      "timeIndexingWithoutContent" : 0,
      "roots" : [ ]
    }, {
      "providerName" : "Indexable set contributor 'com.intellij.httpClient.http.request.run.HttpClientDynamicVariablesStubController@27d1b85f' (non-project)",
      "numberOfScannedFiles" : 1,
      "numberOfSkippedFiles" : 0,
      "numberOfFilesForIndexing" : 0,
      "numberOfFilesFullyIndexedByInfrastructureExtensions" : 0,
      "filesFullyIndexedByInfrastructureExtensions" : [ ],
      "statusTime" : 28437333,
      "scanningTime" : 28446042,
      "timeProcessingUpToDateFiles" : 2401584,
      "timeUpdatingContentLessIndexes" : 5375,
      "timeIndexingWithoutContent" : 0,
      "roots" : [ ]
    }, {
      "providerName" : "Indexable set contributor 'com.intellij.httpClient.http.request.HttpRequestCollectionProvider@7d7b0915' (project)",
      "numberOfScannedFiles" : 0,
      "numberOfSkippedFiles" : 0,
      "numberOfFilesForIndexing" : 0,
      "numberOfFilesFullyIndexedByInfrastructureExtensions" : 0,
      "filesFullyIndexedByInfrastructureExtensions" : [ ],
      "statusTime" : 0,
      "scanningTime" : 0,
      "timeProcessingUpToDateFiles" : 0,
      "timeUpdatingContentLessIndexes" : 0,
      "timeIndexingWithoutContent" : 0,
      "roots" : [ ]
    }, {
      "providerName" : "Indexable set contributor 'Scratches & Consoles' (project)",
      "numberOfScannedFiles" : 0,
      "numberOfSkippedFiles" : 0,
      "numberOfFilesForIndexing" : 0,
      "numberOfFilesFullyIndexedByInfrastructureExtensions" : 0,
      "filesFullyIndexedByInfrastructureExtensions" : [ ],
      "statusTime" : 0,
      "scanningTime" : 0,
      "timeProcessingUpToDateFiles" : 0,
      "timeUpdatingContentLessIndexes" : 0,
      "timeIndexingWithoutContent" : 0,
      "roots" : [ ]
    }, {
      "providerName" : "Indexable set contributor 'com.intellij.javaee.ExternalResourcesRootsProvider@29ec2b36' (project)",
      "numberOfScannedFiles" : 0,
      "numberOfSkippedFiles" : 0,
      "numberOfFilesForIndexing" : 0,
      "numberOfFilesFullyIndexedByInfrastructureExtensions" : 0,
      "filesFullyIndexedByInfrastructureExtensions" : [ ],
      "statusTime" : 0,
      "scanningTime" : 0,
      "timeProcessingUpToDateFiles" : 0,
      "timeUpdatingContentLessIndexes" : 0,
      "timeIndexingWithoutContent" : 0,
      "roots" : [ ]
    }, {
      "providerName" : "Indexable set contributor 'com.intellij.httpClient.http.request.run.HttpClientDynamicVariablesStubController@27d1b85f' (project)",
      "numberOfScannedFiles" : 0,
      "numberOfSkippedFiles" : 0,
      "numberOfFilesForIndexing" : 0,
      "numberOfFilesFullyIndexedByInfrastructureExtensions" : 0,
      "filesFullyIndexedByInfrastructureExtensions" : [ ],
      "statusTime" : 0,
      "scanningTime" : 0,
      "timeProcessingUpToDateFiles" : 0,
      "timeUpdatingContentLessIndexes" : 0,
      "timeIndexingWithoutContent" : 0,
      "roots" : [ ]
    }, {
      "providerName" : "Indexable set contributor 'org.jetbrains.plugins.scss.index.SassScssIndexedRootProvider@112603f9' (project)",
      "numberOfScannedFiles" : 0,
      "numberOfSkippedFiles" : 0,
      "numberOfFilesForIndexing" : 0,
      "numberOfFilesFullyIndexedByInfrastructureExtensions" : 0,
      "filesFullyIndexedByInfrastructureExtensions" : [ ],
      "statusTime" : 0,
      "scanningTime" : 0,
      "timeProcessingUpToDateFiles" : 0,
      "timeUpdatingContentLessIndexes" : 0,
      "timeIndexingWithoutContent" : 0,
      "roots" : [ ]
    }, {
      "providerName" : "Indexable set contributor 'TypeScript bundled libraries' (non-project)",
      "numberOfScannedFiles" : 0,
      "numberOfSkippedFiles" : 0,
      "numberOfFilesForIndexing" : 0,
      "numberOfFilesFullyIndexedByInfrastructureExtensions" : 0,
      "filesFullyIndexedByInfrastructureExtensions" : [ ],
      "statusTime" : 0,
      "scanningTime" : 0,
      "timeProcessingUpToDateFiles" : 0,
      "timeUpdatingContentLessIndexes" : 0,
      "timeIndexingWithoutContent" : 0,
      "roots" : [ ]
    } ],
    "fileProviderStatistics" : [ ],
    "visibleTimeToAllThreadTimeRatio" : 0.0
  }
}