{
  "appInfo" : {
    "build" : "222.4345.14",
    "buildDate" : "2022-10-05T05:01:59.328Z[UTC]",
    "productCode" : "WS",
    "generated" : "2023-03-28T22:27:02.981391Z",
    "os" : "macOS 12.3.1",
    "runtime" : "JetBrains s.r.o. 17.0.4.1 17.0.4.1+7-b469.62"
  },
  "runtimeInfo" : {
    "maxMemory" : 536870912,
    "numberOfProcessors" : 8,
    "maxNumberOfIndexingThreads" : 4,
    "maxSizeOfFileForIntelliSense" : 2560000,
    "maxSizeOfFileForContentLoading" : 20971520
  },
  "projectIndexingHistory" : {
    "projectName" : "locationTest",
    "times" : {
      "indexingReason" : "On project open",
      "scanningType" : "FULL_ON_PROJECT_OPEN",
      "totalUpdatingTime" : 516235542,
      "indexingTime" : 0,
      "contentLoadingVisibleTime" : 0,
      "creatingIteratorsTime" : 1783000,
      "scanFilesTime" : 441483000,
      "pushPropertiesTime" : 28000,
      "indexExtensionsTime" : 0,
      "isAppliedAllValuesSeparately" : true,
      "separateApplyingIndexesVisibleTime" : 0,
      "updatingStart" : "2023-03-28T22:27:02.462083Z",
      "updatingEnd" : "2023-03-28T22:27:02.978323Z",
      "totalSuspendedTime" : 0,
      "wasInterrupted" : false
    },
    "fileCount" : {
      "numberOfFileProviders" : 16,
      "numberOfScannedFiles" : 438,
      "numberOfFilesIndexedByInfrastructureExtensionsDuringScan" : 0,
      "numberOfFilesScheduledForIndexingAfterScan" : 0,
      "numberOfFilesIndexedByInfrastructureExtensionsDuringIndexingStage" : 0,
      "numberOfFilesIndexedWithLoadingContent" : 0
    },
    "totalStatsPerFileType" : [ ],
    "totalStatsPerIndexer" : [ ],
    "scanningStatistics" : [ {
      "providerName" : "Indexable set contributor 'com.intellij.javaee.ExternalResourcesRootsProvider@34a0a6e' (non-project)",
      "numberOfScannedFiles" : 218,
      "numberOfSkippedFiles" : 4,
      "numberOfFilesForIndexing" : 0,
      "numberOfFilesFullyIndexedByInfrastructureExtensions" : 0,
      "filesFullyIndexedByInfrastructureExtensions" : [ ],
      "statusTime" : 152633456,
      "scanningTime" : 157735449,
      "timeProcessingUpToDateFiles" : 29787191,
      "timeUpdatingContentLessIndexes" : 240873,
      "timeIndexingWithoutContent" : 0,
      "roots" : [ ]
    }, {
      "providerName" : "Indexable set contributor 'JS required libraries' (project)",
      "numberOfScannedFiles" : 37,
      "numberOfSkippedFiles" : 41,
      "numberOfFilesForIndexing" : 0,
      "numberOfFilesFullyIndexedByInfrastructureExtensions" : 0,
      "filesFullyIndexedByInfrastructureExtensions" : [ ],
      "statusTime" : 105154665,
      "scanningTime" : 105299879,
      "timeProcessingUpToDateFiles" : 59330041,
      "timeUpdatingContentLessIndexes" : 109127,
      "timeIndexingWithoutContent" : 0,
      "roots" : [ ]
    }, {
      "providerName" : "Indexable set contributor 'Scratches & Consoles' (non-project)",
      "numberOfScannedFiles" : 24,
      "numberOfSkippedFiles" : 0,
      "numberOfFilesForIndexing" : 0,
      "numberOfFilesFullyIndexedByInfrastructureExtensions" : 0,
      "filesFullyIndexedByInfrastructureExtensions" : [ ],
      "statusTime" : 77715129,
      "scanningTime" : 81914919,
      "timeProcessingUpToDateFiles" : 42733003,
      "timeUpdatingContentLessIndexes" : 58044,
      "timeIndexingWithoutContent" : 0,
      "roots" : [ ]
    }, {
      "providerName" : "Synthetic library 'Node.js Core'",
      "numberOfScannedFiles" : 88,
      "numberOfSkippedFiles" : 0,
      "numberOfFilesForIndexing" : 0,
      "numberOfFilesFullyIndexedByInfrastructureExtensions" : 0,
      "filesFullyIndexedByInfrastructureExtensions" : [ ],
      "statusTime" : 74853664,
      "scanningTime" : 78929836,
      "timeProcessingUpToDateFiles" : 22787752,
      "timeUpdatingContentLessIndexes" : 121753,
      "timeIndexingWithoutContent" : 0,
      "roots" : [ ]
    }, {
      "providerName" : "Indexable set contributor 'TypeScript bundled libraries' (project)",
      "numberOfScannedFiles" : 40,
      "numberOfSkippedFiles" : 31,
      "numberOfFilesForIndexing" : 0,
      "numberOfFilesFullyIndexedByInfrastructureExtensions" : 0,
      "filesFullyIndexedByInfrastructureExtensions" : [ ],
      "statusTime" : 61977084,
      "scanningTime" : 62141253,
      "timeProcessingUpToDateFiles" : 47274837,
      "timeUpdatingContentLessIndexes" : 121251,
      "timeIndexingWithoutContent" : 0,
      "roots" : [ ]
    }, {
      "providerName" : "Module 'locationTest' (locationTest)",
      "numberOfScannedFiles" : 8,
      "numberOfSkippedFiles" : 0,
      "numberOfFilesForIndexing" : 0,
      "numberOfFilesFullyIndexedByInfrastructureExtensions" : 0,
      "filesFullyIndexedByInfrastructureExtensions" : [ ],
      "statusTime" : 46267584,
      "scanningTime" : 50766208,
      "timeProcessingUpToDateFiles" : 3392251,
      "timeUpdatingContentLessIndexes" : 26166,
      "timeIndexingWithoutContent" : 0,
      "roots" : [ ]
    }, {
      "providerName" : "Indexable set contributor 'com.intellij.httpClient.http.request.HttpRequestCollectionProvider@454b68dd' (non-project)",
      "numberOfScannedFiles" : 2,
      "numberOfSkippedFiles" : 0,
      "numberOfFilesForIndexing" : 0,
      "numberOfFilesFullyIndexedByInfrastructureExtensions" : 0,
      "filesFullyIndexedByInfrastructureExtensions" : [ ],
      "statusTime" : 38661542,
      "scanningTime" : 42514710,
      "timeProcessingUpToDateFiles" : 6607541,
      "timeUpdatingContentLessIndexes" : 5042,
      "timeIndexingWithoutContent" : 0,
      "roots" : [ ]
    }, {
      "providerName" : "Indexable set contributor 'com.intellij.httpClient.http.request.run.HttpClientDynamicVariablesStubController@7148291a' (non-project)",
      "numberOfScannedFiles" : 1,
      "numberOfSkippedFiles" : 0,
      "numberOfFilesForIndexing" : 0,
      "numberOfFilesFullyIndexedByInfrastructureExtensions" : 0,
      "filesFullyIndexedByInfrastructureExtensions" : [ ],
      "statusTime" : 39303167,
      "scanningTime" : 39307375,
      "timeProcessingUpToDateFiles" : 9827748,
      "timeUpdatingContentLessIndexes" : 2041,
      "timeIndexingWithoutContent" : 0,
      "roots" : [ ]
    }, {
      "providerName" : "Indexable set contributor 'org.jetbrains.plugins.scss.index.SassScssIndexedRootProvider@6263989f' (non-project)",
      "numberOfScannedFiles" : 8,
      "numberOfSkippedFiles" : 0,
      "numberOfFilesForIndexing" : 0,
      "numberOfFilesFullyIndexedByInfrastructureExtensions" : 0,
      "filesFullyIndexedByInfrastructureExtensions" : [ ],
      "statusTime" : 37953706,
      "scanningTime" : 37994000,
      "timeProcessingUpToDateFiles" : 1825628,
      "timeUpdatingContentLessIndexes" : 26166,
      "timeIndexingWithoutContent" : 0,
      "roots" : [ ]
    }, {
      "providerName" : "Indexable set contributor 'JS required libraries' (non-project)",
      "numberOfScannedFiles" : 12,
      "numberOfSkippedFiles" : 0,
      "numberOfFilesForIndexing" : 0,
      "numberOfFilesFullyIndexedByInfrastructureExtensions" : 0,
      "filesFullyIndexedByInfrastructureExtensions" : [ ],
      "statusTime" : 27937875,
      "scanningTime" : 27993001,
      "timeProcessingUpToDateFiles" : 22042877,
      "timeUpdatingContentLessIndexes" : 30460,
      "timeIndexingWithoutContent" : 0,
      "roots" : [ ]
    }, {
      "providerName" : "Indexable set contributor 'com.intellij.httpClient.http.request.HttpRequestCollectionProvider@454b68dd' (project)",
      "numberOfScannedFiles" : 0,
      "numberOfSkippedFiles" : 0,
      "numberOfFilesForIndexing" : 0,
      "numberOfFilesFullyIndexedByInfrastructureExtensions" : 0,
      "filesFullyIndexedByInfrastructureExtensions" : [ ],
      "statusTime" : 0,
      "scanningTime" : 0,
      "timeProcessingUpToDateFiles" : 0,
      "timeUpdatingContentLessIndexes" : 0,
      "timeIndexingWithoutContent" : 0,
      "roots" : [ ]
    }, {
      "providerName" : "Indexable set contributor 'Scratches & Consoles' (project)",
      "numberOfScannedFiles" : 0,
      "numberOfSkippedFiles" : 0,
      "numberOfFilesForIndexing" : 0,
      "numberOfFilesFullyIndexedByInfrastructureExtensions" : 0,
      "filesFullyIndexedByInfrastructureExtensions" : [ ],
      "statusTime" : 0,
      "scanningTime" : 0,
      "timeProcessingUpToDateFiles" : 0,
      "timeUpdatingContentLessIndexes" : 0,
      "timeIndexingWithoutContent" : 0,
      "roots" : [ ]
    }, {
      "providerName" : "Indexable set contributor 'com.intellij.javaee.ExternalResourcesRootsProvider@34a0a6e' (project)",
      "numberOfScannedFiles" : 0,
      "numberOfSkippedFiles" : 0,
      "numberOfFilesForIndexing" : 0,
      "numberOfFilesFullyIndexedByInfrastructureExtensions" : 0,
      "filesFullyIndexedByInfrastructureExtensions" : [ ],
      "statusTime" : 0,
      "scanningTime" : 0,
      "timeProcessingUpToDateFiles" : 0,
      "timeUpdatingContentLessIndexes" : 0,
      "timeIndexingWithoutContent" : 0,
      "roots" : [ ]
    }, {
      "providerName" : "Indexable set contributor 'com.intellij.httpClient.http.request.run.HttpClientDynamicVariablesStubController@7148291a' (project)",
      "numberOfScannedFiles" : 0,
      "numberOfSkippedFiles" : 0,
      "numberOfFilesForIndexing" : 0,
      "numberOfFilesFullyIndexedByInfrastructureExtensions" : 0,
      "filesFullyIndexedByInfrastructureExtensions" : [ ],
      "statusTime" : 0,
      "scanningTime" : 0,
      "timeProcessingUpToDateFiles" : 0,
      "timeUpdatingContentLessIndexes" : 0,
      "timeIndexingWithoutContent" : 0,
      "roots" : [ ]
    }, {
      "providerName" : "Indexable set contributor 'org.jetbrains.plugins.scss.index.SassScssIndexedRootProvider@6263989f' (project)",
      "numberOfScannedFiles" : 0,
      "numberOfSkippedFiles" : 0,
      "numberOfFilesForIndexing" : 0,
      "numberOfFilesFullyIndexedByInfrastructureExtensions" : 0,
      "filesFullyIndexedByInfrastructureExtensions" : [ ],
      "statusTime" : 0,
      "scanningTime" : 0,
      "timeProcessingUpToDateFiles" : 0,
      "timeUpdatingContentLessIndexes" : 0,
      "timeIndexingWithoutContent" : 0,
      "roots" : [ ]
    }, {
      "providerName" : "Indexable set contributor 'TypeScript bundled libraries' (non-project)",
      "numberOfScannedFiles" : 0,
      "numberOfSkippedFiles" : 0,
      "numberOfFilesForIndexing" : 0,
      "numberOfFilesFullyIndexedByInfrastructureExtensions" : 0,
      "filesFullyIndexedByInfrastructureExtensions" : [ ],
      "statusTime" : 0,
      "scanningTime" : 0,
      "timeProcessingUpToDateFiles" : 0,
      "timeUpdatingContentLessIndexes" : 0,
      "timeIndexingWithoutContent" : 0,
      "roots" : [ ]
    } ],
    "fileProviderStatistics" : [ ],
    "visibleTimeToAllThreadTimeRatio" : 0.0
  }
}